click_skeleton/__init__.py
click_skeleton/advanced_group.py
click_skeleton/backtrace.py
click_skeleton/core.py
click_skeleton/decorators.py
click_skeleton/defaults.py
click_skeleton/doc.py
click_skeleton/exceptions.py
click_skeleton/expanded_path.py
click_skeleton/helpers.py
click_skeleton/py.typed
click_skeleton/testing.py
click_skeleton/version.py
click_skeleton/version_checker.py
click_skeleton-0.33.1.dist-info/METADATA
click_skeleton-0.33.1.dist-info/WHEEL
click_skeleton-0.33.1.dist-info/licenses/LICENSE-MIT
click_skeleton-0.33.1.dist-info/RECORD
