Metadata-Version: 2.4
Name: click-skeleton
Version: 0.33.1
Summary: Click app skeleton
Author-email: Adrien Pensart <crunchengine@gmail.com>
License: MIT License
License-File: LICENSE-MIT
Classifier: Development Status :: 5 - Production/Stable
Classifier: Environment :: Console
Classifier: Intended Audience :: Developers
Classifier: License :: OSI Approved :: Apache Software License
Classifier: License :: OSI Approved :: MIT License
Classifier: Operating System :: OS Independent
Classifier: Programming Language :: Python
Classifier: Programming Language :: Python :: 3 :: Only
Classifier: Programming Language :: Python :: 3.12
Classifier: Programming Language :: Python :: 3.13
Requires-Python: >=3.12
Requires-Dist: beartype>=0.20
Requires-Dist: click-aliases>=1.0.1
Requires-Dist: click-didyoumean>=0.3.0
Requires-Dist: click-help-colors>=0.9
Requires-Dist: click-option-group>=0.5.1
Requires-Dist: click>=8.1.8
Requires-Dist: dotmap>=1.3.30
Requires-Dist: requests>=2.24.0
Requires-Dist: semver>=3.0.4
Requires-Dist: types-requests>=2.32.0
